SequencingSolver/EDD.py
SequencingSolver/LCL.py
SequencingSolver/WDSPT.py
SequencingSolver/WSPT.py
SequencingSolver/__init__.py
SequencingSolver/hodgson.py
SequencingSolver/minimizeSumCjWithDeadline.py
SequencingSolver-1.0.3.dist-info/LICENSE.txt
SequencingSolver-1.0.3.dist-info/METADATA
SequencingSolver-1.0.3.dist-info/WHEEL
SequencingSolver-1.0.3.dist-info/top_level.txt
SequencingSolver-1.0.3.dist-info/RECORD
